crossvector/__init__.py
crossvector/abc.py
crossvector/constants.py
crossvector/engine.py
crossvector/exceptions.py
crossvector/logger.py
crossvector/schema.py
crossvector/settings.py
crossvector/types.py
crossvector/utils.py
crossvector/dbs/__init__.py
crossvector/dbs/astradb.py
crossvector/dbs/chroma.py
crossvector/dbs/milvus.py
crossvector/dbs/pgvector.py
crossvector/embeddings/__init__.py
crossvector/embeddings/gemini.py
crossvector/embeddings/openai.py
crossvector/querydsl/__init__.py
crossvector/querydsl/q.py
crossvector/querydsl/compilers/__init__.py
crossvector/querydsl/compilers/astradb.py
crossvector/querydsl/compilers/base.py
crossvector/querydsl/compilers/chroma.py
crossvector/querydsl/compilers/milvus.py
crossvector/querydsl/compilers/pgvector.py
crossvector/querydsl/compilers/utils.py
crossvector-1.0.1.dist-info/METADATA
crossvector-1.0.1.dist-info/WHEEL
crossvector-1.0.1.dist-info/licenses/LICENSE
crossvector-1.0.1.dist-info/RECORD
