Metadata-Version: 2.4
Name: crossvector
Version: 1.0.1
Summary: Cross-platform vector database engine with pluggable adapters
Project-URL: Homepage, https://github.com/thewebscraping/crossvector
Project-URL: Repository, https://github.com/thewebscraping/crossvector
Project-URL: Documentation, https://github.com/thewebscraping/crossvector#readme
Project-URL: Bug Tracker, https://github.com/thewebscraping/crossvector/issues
Author-email: Two Dev <thetwofarm@gmail.com>
Maintainer-email: Two Dev <thetwofarm@gmail.com>
License: MIT
License-File: LICENSE
Keywords: astradb,chromadb,cross-platform,embeddings,llm,milvus,pgvector,rag,semantic-search,vector-database
Classifier: Development Status :: 4 - Beta
Classifier: Intended Audience :: Developers
Classifier: License :: OSI Approved :: MIT License
Classifier: Programming Language :: Python :: 3
Classifier: Programming Language :: Python :: 3.11
Classifier: Programming Language :: Python :: 3.12
Classifier: Topic :: Database
Classifier: Topic :: Scientific/Engineering :: Artificial Intelligence
Requires-Python: >=3.11
Requires-Dist: pydantic-settings>=2.11.0
Requires-Dist: pydantic>=2.12.3
Requires-Dist: python-dotenv>=1.0.0
Provides-Extra: all
Requires-Dist: astrapy>=2.1.0; extra == 'all'
Requires-Dist: chromadb>=1.3.4; extra == 'all'
Requires-Dist: google-genai>=0.3.0; extra == 'all'
Requires-Dist: openai>=2.6.1; extra == 'all'
Requires-Dist: pgvector>=0.4.1; extra == 'all'
Requires-Dist: psycopg2-binary>=2.9.11; extra == 'all'
Requires-Dist: pymilvus>=2.6.4; extra == 'all'
Provides-Extra: all-dbs
Requires-Dist: astrapy>=2.1.0; extra == 'all-dbs'
Requires-Dist: chromadb>=1.3.4; extra == 'all-dbs'
Requires-Dist: pgvector>=0.4.1; extra == 'all-dbs'
Requires-Dist: psycopg2-binary>=2.9.11; extra == 'all-dbs'
Requires-Dist: pymilvus>=2.6.3; extra == 'all-dbs'
Provides-Extra: all-embeddings
Requires-Dist: google-genai>=0.3.0; extra == 'all-embeddings'
Requires-Dist: openai>=2.6.1; extra == 'all-embeddings'
Provides-Extra: astradb
Requires-Dist: astrapy>=2.1.0; extra == 'astradb'
Provides-Extra: chromadb
Requires-Dist: chromadb>=1.3.4; extra == 'chromadb'
Provides-Extra: dev
Requires-Dist: mkdocs-material>=9.5.0; extra == 'dev'
Requires-Dist: mkdocstrings[python]>=0.24.0; extra == 'dev'
Requires-Dist: mypy>=1.18.2; extra == 'dev'
Requires-Dist: pre-commit>=4.0.0; extra == 'dev'
Requires-Dist: pytest-asyncio>=0.23.0; extra == 'dev'
Requires-Dist: pytest-cov>=4.1.0; extra == 'dev'
Requires-Dist: pytest>=8.4.2; extra == 'dev'
Requires-Dist: ruff>=0.13.3; extra == 'dev'
Provides-Extra: gemini
Requires-Dist: google-genai>=0.3.0; extra == 'gemini'
Provides-Extra: milvus
Requires-Dist: pymilvus>=2.6.4; extra == 'milvus'
Provides-Extra: openai
Requires-Dist: openai>=2.6.1; extra == 'openai'
Provides-Extra: pgvector
Requires-Dist: pgvector>=0.4.1; extra == 'pgvector'
Requires-Dist: psycopg2-binary>=2.9.11; extra == 'pgvector'
